otoconf/__init__.py
otoconf/__main__.py
otoconf/resolvers.py
otoconf-0.1.0.dist-info/LICENSE
otoconf-0.1.0.dist-info/WHEEL
otoconf-0.1.0.dist-info/METADATA
otoconf-0.1.0.dist-info/RECORD
