Metadata-Version: 2.1
Name: otoconf
Version: 0.1.0
Summary: oto generate configuration for proxy tools.
Home-page: https://github.com/BilalAlpaslan/otoconf
License: LICENSE
Author: Bilal Alpaslan
Author-email: m.bilal.alpaslan@gmail.com
Requires-Python: >=3.7
Classifier: License :: Other/Proprietary License
Classifier: Programming Language :: Python :: 3
Classifier: Programming Language :: Python :: 3.10
Classifier: Programming Language :: Python :: 3.7
Classifier: Programming Language :: Python :: 3.8
Classifier: Programming Language :: Python :: 3.9
Requires-Dist: nginxfmt (>=0.1.0)
Requires-Dist: typer (>=0.3.0)
